streaming_statistics/__init__.py
streaming_statistics/cli.py
streaming_statistics/stats.py
streaming_statistics-1.0.2.dist-info/METADATA
streaming_statistics-1.0.2.dist-info/WHEEL
streaming_statistics-1.0.2.dist-info/entry_points.txt
streaming_statistics-1.0.2.dist-info/RECORD
