Metadata-Version: 2.1
Name: streaming-statistics
Version: 1.0.2
Summary: A streaming statistics library
Author: Will Fitzgerald
Author-email: willf@users.noreply.github.com
Requires-Python: >=3.9
Classifier: Programming Language :: Python :: 3
Classifier: Programming Language :: Python :: 3.9
Classifier: Programming Language :: Python :: 3.10
Classifier: Programming Language :: Python :: 3.11
Classifier: Programming Language :: Python :: 3.12
Requires-Dist: ddsketch (>=3.0.1,<4.0.0)
